{
  "db_name": "PostgreSQL",
  "query": "\n        SELECT id, label\n        FROM labels l\n        JOIN transaction_labels tl\n            ON l.id = tl.label_id\n        WHERE\n            tl.connection_id = $1\n        AND tl.account_id = $2\n        AND tl.transaction_id = $3\n        ORDER BY\n            l.label ASC\n            ",
  "describe": {
    "columns": [
      {
        "ordinal": 0,
        "name": "id",
        "type_info": "Uuid"
      },
      {
        "ordinal": 1,
        "name": "label",
        "type_info": {
          "Custom": {
            "name": "ltree",
            "kind": "Simple"
          }
        }
      }
    ],
    "parameters": {
      "Left": [
        "Uuid",
        "Text",
        "Text"
      ]
    },
    "nullable": [
      false,
      false
    ]
  },
  "hash": "a1904dba8538ebaa3f57902463a070a2da788e12d60c1ccfdbd2f93bcddac027"
}
